Fileprank/__init__.py
Fileprank-1.0.1.dist-info/METADATA
Fileprank-1.0.1.dist-info/WHEEL
Fileprank-1.0.1.dist-info/top_level.txt
Fileprank-1.0.1.dist-info/RECORD
