Metadata-Version: 2.1
Name: Fileprank
Version: 1.0.1
Summary: prank.create()
Home-page: https://github.com/GGman25/Prank
Author: 4ebureker
Author-email: ggman2555@gmail.com
License: UNKNOWN
Platform: UNKNOWN
Classifier: Programming Language :: Python :: 3
Classifier: License :: OSI Approved :: MIT License
Classifier: Operating System :: OS Independent
Requires-Python: >=3.6
